jinqingutils/__init__.py
jinqingutils/start.py
jinqingutils-0.0.1.dist-info/METADATA
jinqingutils-0.0.1.dist-info/WHEEL
jinqingutils-0.0.1.dist-info/top_level.txt
jinqingutils-0.0.1.dist-info/RECORD
